Metadata-Version: 1.0
Name: ndistbdist
Version: 0.3
Summary: Gaussian and Binomial distributions
Home-page: UNKNOWN
Author: ['Garvit Kataria']
Author-email: UNKNOWN
License: UNKNOWN
Platform: UNKNOWN
